aworkflow/__init__.py
aworkflow/core/run_wrappers.py
aworkflow/core/runner.py
async_workflow_runner-0.1.2.dist-info/AUTHORS.rst
async_workflow_runner-0.1.2.dist-info/LICENSE
async_workflow_runner-0.1.2.dist-info/METADATA
async_workflow_runner-0.1.2.dist-info/WHEEL
async_workflow_runner-0.1.2.dist-info/top_level.txt
async_workflow_runner-0.1.2.dist-info/RECORD
